{"content":[{"id":"62ae96e1","settings":{"stretch_section":"section-stretched","background_background":"gradient","background_color":"#0064FF","background_color_b":"#0F2878","background_overlay_background":"gradient","background_overlay_color_b":"#1B1324","animation":"fadeInRight","margin":{"unit":"px","top":"0","right":0,"bottom":"0","left":0,"isLinked":false},"pa_condition_repeater":[],"layout":"full_width","background_gradient_angle":{"unit":"deg","size":150,"sizes":[]},"padding":{"unit":"px","top":"25","right":"0","bottom":"25","left":"0","isLinked":false}},"elements":[{"id":"349e9082","settings":{"_column_size":100,"_inline_size":null,"pa_condition_repeater":[]},"elements":[{"id":"1d6e58a3","settings":{"anchor":"participantes","pa_condition_repeater":[]},"elements":[],"isInner":false,"widgetType":"menu-anchor","elType":"widget"},{"id":"581809ef","settings":{"title":"Este curso es para ti si:","title_color":"#FFFFFF","_margin":{"unit":"px","top":"0","right":"0","bottom":"0","left":"0","isLinked":false},"_margin_mobile":{"unit":"px","top":"040","right":"0","bottom":"0","left":"0","isLinked":false},"pa_condition_repeater":[]},"elements":[],"isInner":false,"widgetType":"heading","elType":"widget"},{"id":"57f2c36c","settings":{"html":"<style>\n    .lista{\n        list-style: none;\n        color: #fff;\n        margin: 0;\n        font-size: 20px;\n    }\n    \n    .lista li:before{\n        color:#FF5433;\n        content: '\u29bf '\n    }\n<\/style>\n\n<ul class=\"lista\">\n    <li>Lorem Impsum<\/li>\n    <li>Lorem Impsum<\/li>\n    <li>Lorem Impsum<\/li>\n    <li>Lorem Impsum<\/li>\n    <li>Lorem Impsum<\/li>\n<\/ul>","_margin":{"unit":"px","top":"0","right":"0","bottom":"040","left":"0","isLinked":false},"_margin_mobile":{"unit":"px","top":"0","right":"0","bottom":"040","left":"0","isLinked":false},"pa_condition_repeater":[]},"elements":[],"isInner":false,"widgetType":"html","elType":"widget"}],"isInner":false,"elType":"column"}],"isInner":false,"elType":"section"}],"page_settings":[],"version":"0.4","title":"legaltech-curso_para_ti","type":"section"}